cellarium/cas/__init__.py
cellarium/cas/_io.py
cellarium/cas/client.py
cellarium/cas/constants.py
cellarium/cas/endpoints.py
cellarium/cas/exceptions.py
cellarium/cas/logging.py
cellarium/cas/models.py
cellarium/cas/service.py
cellarium/cas/settings.py
cellarium/cas/version.py
cellarium/cas/assets/cellarium_cas_tx_pca_002_grch38_2020_a.json
cellarium/cas/postprocessing/__init__.py
cellarium/cas/postprocessing/cell_type_summary_statistics.py
cellarium/cas/postprocessing/common.py
cellarium/cas/postprocessing/ontology_aware.py
cellarium/cas/postprocessing/cell_ontology/__init__.py
cellarium/cas/postprocessing/cell_ontology/cell_ontology_cache.py
cellarium/cas/preprocessing/__init__.py
cellarium/cas/preprocessing/callbacks.py
cellarium/cas/preprocessing/sanitizer.py
cellarium/cas/preprocessing/validator.py
cellarium/cas/resources/feedback_template.html
cellarium/cas/resources/low_quota_feedback_template.html
cellarium/cas/visualization/__init__.py
cellarium/cas/visualization/ui_utils.py
cellarium/cas/visualization/_components/__init__.py
cellarium/cas/visualization/_components/circular_tree_plot.py
cellarium/cas/visualization/circular_tree_plot_umap_dash_app/__init__.py
cellarium/cas/visualization/circular_tree_plot_umap_dash_app/app.py
cellarium/cas/visualization/circular_tree_plot_umap_dash_app/assets/cellarium-powered-400px.png
cellarium/cas/visualization/circular_tree_plot_umap_dash_app/assets/styles.css
cellarium_cas-1.7.4.dist-info/licenses/LICENSE
cellarium_cas-1.7.4.dist-info/METADATA
cellarium_cas-1.7.4.dist-info/WHEEL
cellarium_cas-1.7.4.dist-info/top_level.txt
cellarium_cas-1.7.4.dist-info/RECORD
