Metadata-Version: 2.4
Name: cellarium-cas
Version: 1.7.4
Summary: Cellarium Cell Annotation Service client tool
Author-email: Cellarium CAS <cas-support@broadinstitute.org>
License: BSD 3-Clause License
Project-URL: Homepage, https://cellarium.ai
Project-URL: Source Code, https://github.com/cellarium-ai/cellarium-cas
Project-URL: Bug Tracker, https://github.com/cellarium-ai/cellarium-cas/issues
Project-URL: Discussion Forum, https://github.com/cellarium-ai/cellarium-cas/discussions
Classifier: Intended Audience :: Developers
Classifier: Intended Audience :: Science/Research
Classifier: License :: OSI Approved :: BSD License
Classifier: Operating System :: OS Independent
Classifier: Programming Language :: Python :: 3
Classifier: Programming Language :: Python :: Implementation :: CPython
Requires-Python: >=3.7
License-File: LICENSE
Requires-Dist: aiohttp[speedups]<4,>=3.8
Requires-Dist: requests<2.33,>=2.31
Requires-Dist: anndata<0.9,>=0.8; python_version < "3.12"
Requires-Dist: anndata<0.13,>=0.10; python_version >= "3.12"
Requires-Dist: numpy<1.26,>=1.21; python_version < "3.12"
Requires-Dist: numpy<2.2,>=2.0; python_version >= "3.12"
Requires-Dist: pandas<2.1,>=1.3; python_version < "3.12"
Requires-Dist: pandas>=2.1; python_version >= "3.12"
Requires-Dist: nest_asyncio~=1.5
Requires-Dist: certifi==2024.7.4
Requires-Dist: Deprecated~=1.2
Requires-Dist: tqdm~=4.66
Requires-Dist: typing_extensions~=4.7.1; python_version < "3.10"
Requires-Dist: typing-extensions<5,>=4.10; python_version >= "3.10"
Requires-Dist: owlready2==0.46; python_version < "3.10"
Requires-Dist: owlready2<=0.50; python_version >= "3.10"
Requires-Dist: networkx<=3.5
Requires-Dist: pydantic==2.5.3; python_version <= "3.7"
Requires-Dist: pydantic==2.9.0; python_version > "3.7"
Provides-Extra: docs
Requires-Dist: Pillow>=10.3.0; extra == "docs"
Requires-Dist: Sphinx~=7.4; extra == "docs"
Requires-Dist: sphinx_gallery~=0.14; extra == "docs"
Requires-Dist: sphinx_rtd_theme~=2.0; extra == "docs"
Requires-Dist: sphinx_substitution_extensions==2024.8.6; extra == "docs"
Requires-Dist: setuptools-git-versioning==2.0.0; extra == "docs"
Requires-Dist: autodoc_pydantic==2.2.0; extra == "docs"
Requires-Dist: nbsphinx; extra == "docs"
Requires-Dist: IPython; extra == "docs"
Provides-Extra: test
Requires-Dist: pytest~=7.3; extra == "test"
Requires-Dist: coverage~=4.5; extra == "test"
Requires-Dist: click~=8.0; extra == "test"
Requires-Dist: mockito>=1.5.0; extra == "test"
Requires-Dist: parameterized>=0.9.0; extra == "test"
Provides-Extra: vis
Requires-Dist: scanpy[leiden]<1.10.0,>=1.9.0; python_version < "3.12" and extra == "vis"
Requires-Dist: scanpy[leiden]<1.12.0,>=1.11.0; python_version >= "3.12" and extra == "vis"
Requires-Dist: biopython==1.85; extra == "vis"
Requires-Dist: plotly; extra == "vis"
Requires-Dist: dash==2.17.1; extra == "vis"
Requires-Dist: dash-bootstrap-components==1.6.0; extra == "vis"
Dynamic: license-file
